map_as_object/__init__.py
map_as_object/map_as_object.py
map_as_object-0.0.1.dist-info/LICENSE
map_as_object-0.0.1.dist-info/METADATA
map_as_object-0.0.1.dist-info/WHEEL
map_as_object-0.0.1.dist-info/top_level.txt
map_as_object-0.0.1.dist-info/RECORD
