Metadata-Version: 2.1
Name: map-as-object
Version: 0.0.1
Summary: Define a object via a map of attributes, not by class and constructor
Home-page: https://github.com/tom-010/map-as-object
Author: Thomas Deniffel
Author-email: tdeniffel@gmail.com
License: Apache2
Platform: UNKNOWN
Classifier: Development Status :: 4 - Beta
Classifier: Intended Audience :: Developers
Classifier: Programming Language :: Python
Classifier: Programming Language :: Python :: 3 :: Only
Classifier: Programming Language :: Python :: 3.6
Classifier: Programming Language :: Python :: 3.7
Requires-Python: >=3
